stem_http/__init__.py
stem_http/client.py
stem_http/tor.py
stem_http-0.2.0.dist-info/LICENSE
stem_http-0.2.0.dist-info/METADATA
stem_http-0.2.0.dist-info/WHEEL
stem_http-0.2.0.dist-info/top_level.txt
stem_http-0.2.0.dist-info/RECORD
