Metadata-Version: 2.1
Name: stem-http
Version: 0.2.0
Summary: The stem-http Python package
Author: John Gorman
License: MIT License
Project-URL: Homepage, https://github.com/gormaniac/stem-http
Project-URL: Documentation, https://gormo.co/stem-http/
Requires-Python: >=3.11
License-File: LICENSE
